TheApi/__init__.py
TheApi/api.py
TheApi/func.py
TheApix-1.2.7.dist-info/LICENSE
TheApix-1.2.7.dist-info/METADATA
TheApix-1.2.7.dist-info/WHEEL
TheApix-1.2.7.dist-info/top_level.txt
TheApix-1.2.7.dist-info/RECORD
