Metadata-Version: 2.1
Name: TheApix
Version: 1.2.7
Summary: TheApix is a Python library for asynchronous interactions with various public APIs, enabling diverse functionalities and data retrieval.
Home-page: https://github.com/Vivekkumar-IN/TheApi
Author: Vivek Kumar
License: MIT
Project-URL: Homepage, https://github.com/Vivekkumar-IN/TheApi
Project-URL: Issues, https://github.com/Vivekkumar-IN/TheApi/issues
Project-URL: Source, https://github.com/Vivekkumar-IN/TheApi
Project-URL: Community, https://t.me/TheTeamVivek
Classifier: Programming Language :: Python :: 3.9
Classifier: Programming Language :: Python :: 3.10
Classifier: Programming Language :: Python :: 3.11
Classifier: Programming Language :: Python :: 3.12
Classifier: License :: OSI Approved :: MIT License
Requires-Python: >=3.9
License-File: LICENSE
Requires-Dist: aiohttp
Requires-Dist: aiofiles
Requires-Dist: requests
Requires-Dist: pillow
